src/__init__.py
src/config.py
src/exceptions.py
src/tools/__init__.py
src/tools/banco.py
src/tools/cambio.py
src/tools/cep.py
src/tools/cnpj.py
src/tools/ddd.py
src/tools/feriados.py
src/tools/fipe.py
src/tools/schemas.py
src/tools/taxas.py
src/utils/__init__.py
src/utils/api.py
src/utils/formatters.py
src/utils/validators.py
mseep_mcp_brasil_api-0.1.1.dist-info/METADATA
mseep_mcp_brasil_api-0.1.1.dist-info/WHEEL
mseep_mcp_brasil_api-0.1.1.dist-info/entry_points.txt
mseep_mcp_brasil_api-0.1.1.dist-info/licenses/LICENSE
mseep_mcp_brasil_api-0.1.1.dist-info/RECORD
