Metadata-Version: 2.4
Name: mseep-mcp-brasil-api
Version: 0.1.1
Summary: Servidor MCP (Model Context Protocol) para acesso a dados da Brasil API
Project-URL: Homepage, https://github.com/lucianfialho/mcp-brasil-api
Project-URL: Bug Tracker, https://github.com/lucianfialho/mcp-brasil-api/issues
Author-email: mseep <support@skydeck.ai>
License: MIT
License-File: LICENSE
Requires-Python: >=3.10
Requires-Dist: httpx>=0.28.1
Requires-Dist: mcp[cli]>=1.4.1
Requires-Dist: pydantic>=2.0.0
Requires-Dist: python-dotenv>=1.0.1
